{
  "configVersion": 1,
  "timestamp": 1591349837094,
  "index": "/W98/index.html",
  "assetGroups": [
    {
      "name": "app",
      "installMode": "prefetch",
      "updateMode": "prefetch",
      "urls": [
        "/W98/5-es2015.4ee7b58b2600255b4dee.js",
        "/W98/5-es5.4ee7b58b2600255b4dee.js",
        "/W98/6-es2015.f4ff0cb62bdad11b4a6d.js",
        "/W98/6-es5.f4ff0cb62bdad11b4a6d.js",
        "/W98/favicon.ico",
        "/W98/index.html",
        "/W98/main-es2015.b314f25aade357eb164d.js",
        "/W98/main-es5.b314f25aade357eb164d.js",
        "/W98/manifest.webmanifest",
        "/W98/polyfills-es2015.1f913f16a2d346cc8bdc.js",
        "/W98/polyfills-es5.1a3c78b07cd6f16c6e9a.js",
        "/W98/runtime-es2015.6d453420761878f32e9e.js",
        "/W98/runtime-es5.6d453420761878f32e9e.js",
        "/W98/styles.c1005de13c4d84921451.css"
      ],
      "patterns": []
    },
    {
      "name": "assets",
      "installMode": "lazy",
      "updateMode": "prefetch",
      "urls": [
        "/W98/PerfectDOSVGA437.f8addc081fbe64cdf27c.woff",
        "/W98/PerfectDOSVGA437Win.63529a8a1ea7c39ed646.woff",
        "/W98/assets/defaultConfig.json",
        "/W98/assets/fonts/PerfectDOSVGA437.woff",
        "/W98/assets/fonts/PerfectDOSVGA437Win.woff",
        "/W98/assets/fonts/style.css",
        "/W98/assets/icons/icon-128x128.png",
        "/W98/assets/icons/icon-144x144.png",
        "/W98/assets/icons/icon-152x152.png",
        "/W98/assets/icons/icon-192x192.png",
        "/W98/assets/icons/icon-384x384.png",
        "/W98/assets/icons/icon-512x512.png",
        "/W98/assets/icons/icon-72x72.png",
        "/W98/assets/icons/icon-96x96.png"
      ],
      "patterns": []
    }
  ],
  "dataGroups": [],
  "hashTable": {
    "/W98/5-es2015.4ee7b58b2600255b4dee.js": "2847f13a693280a484fb94b45f45e1dbca6ac0e1",
    "/W98/5-es5.4ee7b58b2600255b4dee.js": "195c3757f53d575163873d5fc01285a674e3ffeb",
    "/W98/6-es2015.f4ff0cb62bdad11b4a6d.js": "9f434791dc23128dd4ab20daefa1fd49dc83b6c1",
    "/W98/6-es5.f4ff0cb62bdad11b4a6d.js": "78fb0c0f8ad2fa11adaa3d8eaaaaa6722bac8d1e",
    "/W98/PerfectDOSVGA437.f8addc081fbe64cdf27c.woff": "efe1bfc36a7cee1c9d59bbf274adf6ebc475b8ba",
    "/W98/PerfectDOSVGA437Win.63529a8a1ea7c39ed646.woff": "cfab137aa2ed0bf9f9e12fa6de7ed82d6e96c0a0",
    "/W98/assets/defaultConfig.json": "bf9fdeb7646739612a4693ff47389a39efe64edd",
    "/W98/assets/fonts/PerfectDOSVGA437.woff": "efe1bfc36a7cee1c9d59bbf274adf6ebc475b8ba",
    "/W98/assets/fonts/PerfectDOSVGA437Win.woff": "cfab137aa2ed0bf9f9e12fa6de7ed82d6e96c0a0",
    "/W98/assets/fonts/style.css": "a192e0cdff067113fc8b35d6ab08bb54ac72f36e",
    "/W98/assets/icons/icon-128x128.png": "dae3b6ed49bdaf4327b92531d4b5b4a5d30c7532",
    "/W98/assets/icons/icon-144x144.png": "b0bd89982e08f9bd2b642928f5391915b74799a7",
    "/W98/assets/icons/icon-152x152.png": "7479a9477815dfd9668d60f8b3b2fba709b91310",
    "/W98/assets/icons/icon-192x192.png": "1abd80d431a237a853ce38147d8c63752f10933b",
    "/W98/assets/icons/icon-384x384.png": "329749cd6393768d3131ed6304c136b1ca05f2fd",
    "/W98/assets/icons/icon-512x512.png": "559d9c4318b45a1f2b10596bbb4c960fe521dbcc",
    "/W98/assets/icons/icon-72x72.png": "c457e56089a36952cd67156f9996bc4ce54a5ed9",
    "/W98/assets/icons/icon-96x96.png": "3914125a4b445bf111c5627875fc190f560daa41",
    "/W98/favicon.ico": "22f6a4a3bcaafafb0254e0f2fa4ceb89e505e8b2",
    "/W98/index.html": "c503b92f4c6394c3bbea672ec0c6dca2ab1ed3ba",
    "/W98/main-es2015.b314f25aade357eb164d.js": "124c55ef80b10b263e188c02e4d00353ce633fc4",
    "/W98/main-es5.b314f25aade357eb164d.js": "473d30d35baa20aee550a6a8b608e47deb0aac65",
    "/W98/manifest.webmanifest": "b798cf5f33c39c3b58e16fadfda78f0f26d6eff4",
    "/W98/polyfills-es2015.1f913f16a2d346cc8bdc.js": "72ad4ccc0a3916ae4598199447cdeadd6d380570",
    "/W98/polyfills-es5.1a3c78b07cd6f16c6e9a.js": "87006d1f609b94ee122cc7790b1ddb5e03d8eaa6",
    "/W98/runtime-es2015.6d453420761878f32e9e.js": "34d91d822c556f8b41ed88f075356e1300f8bd04",
    "/W98/runtime-es5.6d453420761878f32e9e.js": "0b97df0f5f77282c23868a695c66ba7e73adefb0",
    "/W98/styles.c1005de13c4d84921451.css": "0ea549f783283872fddaa3321918f2f1dff2980c"
  },
  "navigationUrls": [
    {
      "positive": true,
      "regex": "^\\/.*$"
    },
    {
      "positive": false,
      "regex": "^\\/(?:.+\\/)?[^/]*\\.[^/]*$"
    },
    {
      "positive": false,
      "regex": "^\\/(?:.+\\/)?[^/]*__[^/]*$"
    },
    {
      "positive": false,
      "regex": "^\\/(?:.+\\/)?[^/]*__[^/]*\\/.*$"
    }
  ]
}